blue_users/__init__.py
blue_users/admin.py
blue_users/apps.py
blue_users/authentication.py
blue_users/models.py
blue_users/tests.py
blue_users/views.py
blue_users/migrations/__init__.py
django_blue_users-2.2.dist-info/LICENCE
django_blue_users-2.2.dist-info/METADATA
django_blue_users-2.2.dist-info/WHEEL
django_blue_users-2.2.dist-info/top_level.txt
django_blue_users-2.2.dist-info/RECORD
