Metadata-Version: 2.1
Name: django-blue-users
Version: 2.2
Summary: Django app users
Home-page: UNKNOWN
Author: Edison
Author-email: echavez.external@bluedraft.com.ar
Maintainer-email: echavez.external@bluedraft.com.ar
License: UNKNOWN
Keywords: django users
Platform: UNKNOWN
Classifier: Environment :: Web Environment
Classifier: Framework :: Django
Classifier: Intended Audience :: Developers
Classifier: License :: OSI Approved :: MIT License
Classifier: Operating System :: OS Independent
Classifier: Programming Language :: Python :: 3
Classifier: Programming Language :: Python :: 3 :: Only
Classifier: Programming Language :: Python :: 3.5
Classifier: Programming Language :: Python :: 3.6
Classifier: Programming Language :: Python :: 3.7
Classifier: Programming Language :: Python :: 3.8
Classifier: Topic :: Software Development :: Libraries :: Python Modules
